[
    {
        "word": "understand",
        "audio": "empty",
        "sentence": "I need to <word> this concept better",
        "difficulty": "Easy"
    },
    {
        "word": "speak",
        "audio": "empty",
        "sentence": "She can <word> multiple languages with confidence",
        "difficulty": "Easy"
    },
    {
        "word": "fluently",
        "audio": "empty",
        "sentence": "He speaks English <word> without any hesitation",
        "difficulty": "Medium"
    },
    {
        "word": "learn",
        "audio": "empty",
        "sentence": "Students <word> new vocabulary every day",
        "difficulty": "Super Easy"
    },
    {
        "word": "practice",
        "audio": "empty",
        "sentence": "You should <word> pronunciation regularly",
        "difficulty": "Medium"
    },
    {
        "word": "improve",
        "audio": "empty",
        "sentence": "Reading books will help <word> your writing skills",
        "difficulty": "Easy"
    },
    {
        "word": "accommodate",
        "audio": "empty",
        "sentence": "The hotel can <word> up to 500 guests",
        "difficulty": "Hard"
    },
    {
        "word": "necessary",
        "audio": "empty",
        "sentence": "It is <word> to bring an umbrella today",
        "difficulty": "Medium"
    },
    {
        "word": "privilege",
        "audio": "empty",
        "sentence": "Attending university is a <word> not a right",
        "difficulty": "Hard"
    },
    {
        "word": "surveillance",
        "audio": "empty",
        "sentence": "The <word> system monitored the entire building",
        "difficulty": "Very Hard"
    },
    {
        "word": "onomatopoeia",
        "audio": "empty",
        "sentence": "The word 'buzz' is an example of <word>",
        "difficulty": "Extreme"
    },
    {
        "word": "antidisestablishmentarianism",
        "audio": "empty",
        "sentence": "The political movement was known for <word>",
        "difficulty": "Extreme"
    }
]
